{"cameraMode":{"drawMode":0,"name":"Shaded","section":"Shading Mode"},"sceneLighting":true,"audioPlay":false,"sceneViewState":{"m_AlwaysRefresh":false,"showFog":true,"showSkybox":true,"showFlares":true,"showImageEffects":true,"showParticleSystems":true,"showVisualEffectGraphs":true,"m_FxEnabled":true},"in2DMode":false,"pivot":{"x":-2.9203133583068849,"y":-6.2875752449035648,"z":8.66218090057373},"rotation":{"x":0.2066507339477539,"y":-0.07770349085330963,"z":0.016442852094769479,"w":0.9752249717712402},"size":10.0,"orthographic":false}